iRSVPred_2/__init__.py
iRSVPred_2/basmati.py
iRSVPred_2-0.1.2.dist-info/METADATA
iRSVPred_2-0.1.2.dist-info/WHEEL
iRSVPred_2-0.1.2.dist-info/top_level.txt
iRSVPred_2-0.1.2.dist-info/RECORD
